inverse_cai/__init__.py
inverse_cai/file_manager.py
inverse_cai/local_secrets.py
inverse_cai/models.py
inverse_cai/models_test.py
inverse_cai/paper_plotting.py
inverse_cai/utils.py
inverse_cai/visualisation.py
inverse_cai/algorithm/__init__.py
inverse_cai/algorithm/cache.py
inverse_cai/algorithm/clustering.py
inverse_cai/algorithm/filter.py
inverse_cai/algorithm/filter_test.py
inverse_cai/algorithm/main.py
inverse_cai/algorithm/main_test.py
inverse_cai/algorithm/proposal.py
inverse_cai/algorithm/utils.py
inverse_cai/algorithm/voting.py
inverse_cai/algorithm/voting_test.py
inverse_cai/annotators/__init__.py
inverse_cai/annotators/alpaca_eval.py
inverse_cai/annotators/core.py
inverse_cai/annotators/dummy.py
inverse_cai/app/__init__.py
inverse_cai/app/builtin_datasets.py
inverse_cai/app/callbacks.py
inverse_cai/app/constants.py
inverse_cai/app/data_loader.py
inverse_cai/app/info_texts.py
inverse_cai/app/interface.py
inverse_cai/app/loader.py
inverse_cai/app/main.py
inverse_cai/app/metrics.py
inverse_cai/app/metrics_test.py
inverse_cai/app/styling.py
inverse_cai/app/plotting/__init__.py
inverse_cai/app/plotting/main.py
inverse_cai/app/plotting/multiple.py
inverse_cai/app/plotting/single.py
inverse_cai/app/plotting/utils.py
inverse_cai/assets/alpacaeval_annotator_configs/alpaca_eval_gpt4o_fn_noinstruction/alpaca_eval_fn.txt
inverse_cai/assets/alpacaeval_annotator_configs/alpaca_eval_gpt4o_fn_noinstruction/configs.yaml
inverse_cai/assets/alpacaeval_annotator_configs/alpaca_eval_gpt4omini_fn_noinstruction/alpaca_eval_fn.txt
inverse_cai/assets/alpacaeval_annotator_configs/alpaca_eval_gpt4omini_fn_noinstruction/configs.yaml
inverse_cai/assets/alpacaeval_annotator_configs/gpt4o_fn_constitutional_base_neutral_v2/configs.yaml
inverse_cai/assets/alpacaeval_annotator_configs/gpt4o_fn_constitutional_base_neutral_v2/constitutional_prompt.txt
inverse_cai/assets/alpacaeval_annotator_configs/gpt4omini_fn_constitutional_base_neutral_v2/configs.yaml
inverse_cai-0.4.6.dist-info/METADATA
inverse_cai-0.4.6.dist-info/WHEEL
inverse_cai-0.4.6.dist-info/entry_points.txt
inverse_cai-0.4.6.dist-info/licenses/LICENSE
inverse_cai-0.4.6.dist-info/RECORD
